{
    "@context": "http://schema.org",
    "@type": "Person",
    "name": "Peter Wilkie",
    "image": "https://i1.rgstatic.net/ii/profile.image/277127858540548-1443083838886_Q128/Peter_Wilkie.jpg",
    "mainEntityOfPage": "https://www.researchgate.net/profile/Peter_Wilkie",
    "url": "https://www.researchgate.net/profile/Peter_Wilkie",
    "affiliation": {
        "@type": "Organization",
        "name": "Royal Botanic Garden Edinburgh",
        "url": "https://www.researchgate.net/institution/Royal_Botanic_Garden_Edinburgh"
    }
}